qoery/__init__.py
qoery/client.py
qoery/exceptions.py
qoery/models.py
qoery/_internal/__init__.py
qoery/_internal/api_client.py
qoery/_internal/api_response.py
qoery/_internal/configuration.py
qoery/_internal/exceptions.py
qoery/_internal/py.typed
qoery/_internal/rest.py
qoery/_internal/api/__init__.py
qoery/_internal/api/account_api.py
qoery/_internal/api/discovery_api.py
qoery/_internal/api/market_data_api.py
qoery/_internal/api/system_api.py
qoery/_internal/models/__init__.py
qoery/_internal/models/candle.py
qoery/_internal/models/candles_response.py
qoery/_internal/models/error.py
qoery/_internal/models/health_response.py
qoery/_internal/models/pool.py
qoery/_internal/models/pools_response.py
qoery/_internal/models/tick.py
qoery/_internal/models/ticks_response.py
qoery/_internal/models/token.py
qoery/_internal/models/usage_response.py
qoery/_internal/models/usage_response_api_calls.py
qoery/_internal/models/usage_response_api_calls_minute.py
qoery/_internal/models/usage_response_api_calls_month.py
qoery/_internal/models/usage_response_credits.py
qoery/_internal/models/usage_response_credits_minute.py
qoery/_internal/models/usage_response_credits_month.py
qoery/resources/__init__.py
qoery/resources/account.py
qoery/resources/candles.py
qoery/resources/pools.py
qoery/resources/ticks.py
qoery-0.6.0.dist-info/licenses/LICENSE
qoery-0.6.0.dist-info/METADATA
qoery-0.6.0.dist-info/WHEEL
qoery-0.6.0.dist-info/top_level.txt
qoery-0.6.0.dist-info/RECORD
