Metadata-Version: 2.4
Name: qoery
Version: 0.6.0
Summary: The Cheapest DeFi Data API - Official Python SDK
Home-page: 
Author: OpenAPI Generator community
Author-email: Qoery Team <contact@qoery.com>
License: MIT
Project-URL: Repository, https://github.com/realfishsam/qoery-py
Project-URL: Homepage, https://qoery.com
Project-URL: Documentation, https://docs.qoery.com
Keywords: qoery,defi,crypto,api,uniswap,dex
Requires-Python: >=3.9
License-File: LICENSE
Requires-Dist: urllib3<3.0.0,>=2.1.0
Requires-Dist: python-dateutil>=2.8.2
Requires-Dist: pydantic<2.5,>=2.4
Requires-Dist: typing-extensions>=4.7.1
Requires-Dist: pandas>=1.3.0
Requires-Dist: python-dotenv>=1.0.0
Dynamic: author
Dynamic: license-file
